marktree/__init__.py
marktree/__main__.py
marktree/cli.py
marktree/core.py
marktree/usage.py
marktree-1.2.0.dist-info/entry_points.txt
marktree-1.2.0.dist-info/licenses/LICENSE
marktree-1.2.0.dist-info/METADATA
marktree-1.2.0.dist-info/WHEEL
marktree-1.2.0.dist-info/RECORD
