Metadata-Version: 2.4
Name: marktree
Version: 1.2.0
Summary: Convert headings in a Markdown file (.md) into a tree-like structure and output.
License: MIT
License-File: LICENSE
Author: yusu79
Author-email: oss@yusu79.com
Requires-Python: >=3.13
Classifier: License :: OSI Approved :: MIT License
Classifier: Programming Language :: Python :: 3
Classifier: Programming Language :: Python :: 3.13
Classifier: Programming Language :: Python :: 3.14
Requires-Dist: pyperclip (>=1.10.0,<2.0.0)
Project-URL: Changelog, https://github.com/yusu79/marktree/blob/main/CHANGELOG.md
Project-URL: Homepage, https://yusu79.com
Project-URL: Repository, https://github.com/yusu79/marktree
